json_schema_to_dash_forms/__init__.py
json_schema_to_dash_forms/forms.py
json_schema_to_dash_forms/utils.py
json_schema_to_dash_forms-0.1.8.dist-info/LICENSE
json_schema_to_dash_forms-0.1.8.dist-info/METADATA
json_schema_to_dash_forms-0.1.8.dist-info/WHEEL
json_schema_to_dash_forms-0.1.8.dist-info/top_level.txt
json_schema_to_dash_forms-0.1.8.dist-info/RECORD
