Metadata-Version: 2.1
Name: json-schema-to-dash-forms
Version: 0.1.8
Summary: JSON schema to Dash forms
Home-page: https://github.com/catalystneuro/json-schema-to-dash-forms
Author: Luiz Tauffer and Vinicius Camozzato Vaz
Author-email: luiz@taufferconsulting.com
License: UNKNOWN
Platform: UNKNOWN
License-File: LICENSE
Requires-Dist: numpy
Requires-Dist: dash
Requires-Dist: dash-bootstrap-components
Requires-Dist: dash-cool-components
